cimloader/batch_handlers/blazegraph_to_mysql.py
cimloader/batch_handlers/naerm_to_neo4j.py
cimloader/databases/__init__.py
cimloader/databases/blazegraph.py
cimloader/databases/mysql.py
cimloader/databases/neo4j.py
cimloader/downloaders/__init__.py
cimloader/downloaders/blazegraph.py
cimloader/downloaders/graphdb.py
cimloader/downloaders/mysql.py
cimloader/downloaders/naerm_api.py
cimloader/downloaders/neo4j.py
cimloader/serializations/encoders/__init__.py
cimloader/serializations/translators/__init__.py
cimloader/uploaders/__init__.py
cimloader/uploaders/blazegraph.py
cimloader/uploaders/graphdb.py
cimloader/uploaders/mysql.py
cimloader/uploaders/neo4j.py
cim_loader-0.1.2a0.dist-info/LICENSE
cim_loader-0.1.2a0.dist-info/METADATA
cim_loader-0.1.2a0.dist-info/WHEEL
cim_loader-0.1.2a0.dist-info/RECORD
