Metadata-Version: 2.1
Name: cim-loader
Version: 0.1.2a0
Summary: CIM Database Uploader & Downloader
Author: A. Anderson
Author-email: 19935503+AAndersn@users.noreply.github.com
Requires-Python: >=3.8.1,<4.0
Classifier: Programming Language :: Python :: 3
Classifier: Programming Language :: Python :: 3.9
Classifier: Programming Language :: Python :: 3.10
Classifier: Programming Language :: Python :: 3.11
Classifier: Programming Language :: Python :: 3.12
Provides-Extra: gridappsd
Requires-Dist: SPARQLWrapper (>=2.0.0,<3.0.0)
Requires-Dist: cim-graph (>=0.1.5a0,<0.2.0)
Requires-Dist: mysql-connector-python (>=8.0.0,<9.0.0)
Requires-Dist: neo4j (>=5.10.0,<6.0.0)
Requires-Dist: rdflib (>=7.0.0,<8.0.0)
Requires-Dist: rdflib-neo4j (>=0.0.1b6,<0.0.2)
Requires-Dist: requests (>=2.28.0,<3.0.0)
